s3minimal/__init__.py
s3minimal/errors.py
s3minimal/s3.py
s3minimal-0.4.dist-info/LICENSE
s3minimal-0.4.dist-info/METADATA
s3minimal-0.4.dist-info/WHEEL
s3minimal-0.4.dist-info/RECORD
