Metadata-Version: 2.1
Name: s3minimal
Version: 0.4
Summary: A Python library designed to simplify interactions with Amazon S3 using the `aiobotocore` and `botocore` libraries. It provides asynchronous and synchronous classes for various S3 operations.
Home-page: https://github.com/jsaied99/s3minimal/
License: MIT
Author: Jamal
Author-email: jsaied99@gmail.com
Requires-Python: >=3.9,<4.0
Classifier: License :: OSI Approved :: MIT License
Classifier: Programming Language :: Python :: 3
Classifier: Programming Language :: Python :: 3.9
Classifier: Programming Language :: Python :: 3.10
Classifier: Programming Language :: Python :: 3.11
Classifier: Programming Language :: Python :: 3.12
Requires-Dist: aiobotocore[boto3] (>=2.6.0,<3.0.0)
Project-URL: Repository, https://github.com/jsaied99/s3minimal/
